pfzy/__init__.py
pfzy/match.py
pfzy/score.py
pfzy/types.py
pfzy-0.3.2.dist-info/LICENSE
pfzy-0.3.2.dist-info/WHEEL
pfzy-0.3.2.dist-info/METADATA
pfzy-0.3.2.dist-info/RECORD
