Metadata-Version: 2.1
Name: pfzy
Version: 0.3.2
Summary: Python port of the fzy fuzzy string matching algorithm
Home-page: https://github.com/kazhala/pfzy
License: MIT
Keywords: fuzzy,string,fzy,search,development
Author: Kevin Zhuang
Author-email: kevin7441@gmail.com
Requires-Python: >=3.7,<4.0
Classifier: Development Status :: 4 - Beta
Classifier: Intended Audience :: Developers
Classifier: License :: OSI Approved :: MIT License
Classifier: Operating System :: Microsoft
Classifier: Operating System :: Unix
Classifier: Programming Language :: Python :: 3
Classifier: Programming Language :: Python :: 3.10
Classifier: Programming Language :: Python :: 3.7
Classifier: Programming Language :: Python :: 3.8
Classifier: Programming Language :: Python :: 3.9
Classifier: Topic :: Software Development
Classifier: Topic :: Software Development :: Libraries
Provides-Extra: docs
Requires-Dist: Sphinx (>=4.1.2,<5.0.0); extra == "docs"
Requires-Dist: furo (>=2021.8.17-beta.43,<2022.0.0); extra == "docs"
Requires-Dist: myst-parser (>=0.15.1,<0.16.0); extra == "docs"
Requires-Dist: sphinx-autobuild (>=2021.3.14,<2022.0.0); extra == "docs"
Requires-Dist: sphinx-copybutton (>=0.4.0,<0.5.0); extra == "docs"
Project-URL: Documentation, https://pfzy.readthedocs.io/
Project-URL: Repository, https://github.com/kazhala/pfzy
